{"gender": {"female": 0, "male": 1}, "Partner": {"yes": 0, "no": 1}, "Dependents": {"no": 0, "yes": 1}, "PhoneService": {"no": 0, "yes": 1}, "MultipleLines": {"no phone service": 0, "no": 1, "yes": 2}, "InternetService": {"dsl": 0, "fiber optic": 1, "no": 2}, "OnlineSecurity": {"no": 0, "yes": 1, "no internet service": 2}, "OnlineBackup": {"yes": 0, "no": 1, "no internet service": 2}, "DeviceProtection": {"no": 0, "yes": 1, "no internet service": 2}, "TechSupport": {"no": 0, "yes": 1, "no internet service": 2}, "StreamingTV": {"no": 0, "yes": 1, "no internet service": 2}, "StreamingMovies": {"no": 0, "yes": 1, "no internet service": 2}, "Contract": {"month-to-month": 0, "one year": 1, "two year": 2}, "PaperlessBilling": {"yes": 0, "no": 1}, "PaymentMethod": {"electronic check": 0, "mailed check": 1, "bank transfer (automatic)": 2, "credit card (automatic)": 3}, "y": {"no": 0, "yes": 1}}